omoikane/__init__.py
omoikane/example.py
omoikane-0.0.1.dist-info/LICENSE
omoikane-0.0.1.dist-info/METADATA
omoikane-0.0.1.dist-info/WHEEL
omoikane-0.0.1.dist-info/RECORD
