Metadata-Version: 2.1
Name: omoikane
Version: 0.0.1
Summary: Neural Network from ground up.
Home-page: https://github.com/SoloSynth1/omoikane
License: MIT
Author: omoikane
Author-email: solosynth1@gmail.com
Requires-Python: >=3.9,<4.0
Classifier: Development Status :: 3 - Alpha
Classifier: Intended Audience :: Developers
Classifier: License :: OSI Approved :: MIT License
Classifier: Operating System :: OS Independent
Classifier: Programming Language :: Python :: 3
Classifier: Programming Language :: Python :: 3.9
Classifier: Programming Language :: Python :: 3.10
Classifier: Programming Language :: Python :: 3.11
Classifier: Programming Language :: Python :: 3.12
Classifier: Topic :: Software Development :: Libraries :: Python Modules
Requires-Dist: numpy (>=1.26.3,<2.0.0)
Project-URL: Repository, https://github.com/SoloSynth1/omoikane
